kul_tools/__init__.py
kul_tools/kul_tools.py
kul_tools/analysis/__init__.py
kul_tools/analysis/nmr.py
kul_tools/analysis/vibrational_frequency.py
kul_tools/utils/__init__.py
kul_tools/utils/element.py
kul_tools/utils/tagging.py
kultools-0.4.dist-info/METADATA
kultools-0.4.dist-info/WHEEL
kultools-0.4.dist-info/top_level.txt
kultools-0.4.dist-info/RECORD
