Metadata-Version: 2.1
Name: kultools
Version: 0.4
Summary: Utility package for atomistic simulations using ASE and VASP
Author-email: Kulkarni Research Group <arkulkarni@ucdavis.edu>
Project-URL: Homepage, https://github.com/kul-group/kultools
Project-URL: Bug Tracker, https://github.com/kul-group/kultools/issues
Classifier: Programming Language :: Python :: 3
Classifier: Programming Language :: Python :: 3.8
Classifier: Programming Language :: Python :: 3.9
Classifier: Programming Language :: Python :: 3.10
Classifier: Development Status :: 4 - Beta
Classifier: Intended Audience :: Science/Research
Classifier: Operating System :: OS Independent
Classifier: Topic :: Scientific/Engineering :: Information Analysis
Classifier: Topic :: Scientific/Engineering :: Physics
Classifier: Topic :: Scientific/Engineering :: Chemistry
Classifier: Topic :: Software Development :: Libraries :: Python Modules
Requires-Python: >=3.6
Requires-Dist: numpy >=1.23
Requires-Dist: scipy >=1.3.1
Requires-Dist: ase >=3.22
